monitorBuilding/__init__.py
monitorBuilding/conf.py
monitorBuilding/monitorBuilding.py
monitorBuilding/parameters_conf.default.py
monitorBuilding/parameters_conf.py
monitorBuilding/confFiles/ALSTOM_GTC TRANE_TABLE ECHANGE MODBUS_14.06.2022.xlsx
monitorBuilding/confFiles/ModbusTCP_Map.xml
monitorBuilding/confFiles/ModbusTCP_Map_2022_05_28.xml
monitorBuilding/confFiles/build_df_gtc_alstom.py
monitorBuilding/confFiles/monitorBuilding_user.md
monitorBuilding/confFiles/monitorbuilding_conf.pkl
monitorBuilding/confFiles/monitorbuilding_configfiles.ods
monitorBuilding/confFiles/monitoring_conf.pkl
monitorBuilding/confFiles/PLC_config/alldfsPLC.pkl
monitorBuilding/confFiles/PLC_config/map_missingTags.pkl
monitorBuilding/confFiles/PLC_config/map_presenceTags.pkl
monitorBuilding/confFiles/PLC_config/nbTags.pkl
monitorBuilding/confFiles/PLC_config/plc_v0.1.csv
monitorBuilding/confFiles/PLC_config/plc_v0.2.csv
monitorBuilding/confFiles/PLC_config/plc_v1.0.csv
monitorBuilding/confFiles/PLC_config/versionnageTags.ods
monitorBuilding-6.3.3.dist-info/METADATA
monitorBuilding-6.3.3.dist-info/WHEEL
monitorBuilding-6.3.3.dist-info/top_level.txt
monitorBuilding-6.3.3.dist-info/RECORD
